jadio_easy_prompter/__init__.py
jadio_easy_prompter/cli/__init__.py
jadio_easy_prompter/cli/clicommands.json
jadio_easy_prompter/cli/main.py
jadio_easy_prompter/core/__init__.py
jadio_easy_prompter-0.0.1.dist-info/METADATA
jadio_easy_prompter-0.0.1.dist-info/WHEEL
jadio_easy_prompter-0.0.1.dist-info/licenses/LICENSE
jadio_easy_prompter-0.0.1.dist-info/RECORD
